bulkfret_analysis/__init__.py
bulkfret_analysis/draap.py
smfret_analysis/__init__.py
smfret_analysis/analyzer.py
smfret_analysis/data_store.py
smfret_analysis/inspector.py
smfret_analysis/inspector_gui.py
smfret_analysis/inspector_gui.qml
smfret_analysis/plotter.py
smfret_analysis/tracker.py
smfret_analysis/version.py
fret_analysis-3.1.0.dist-info/METADATA
fret_analysis-3.1.0.dist-info/WHEEL
fret_analysis-3.1.0.dist-info/licenses/LICENSES/BSD-3-Clause.txt
fret_analysis-3.1.0.dist-info/licenses/LICENSES/CC-BY-4.0.txt
fret_analysis-3.1.0.dist-info/licenses/LICENSES/CC0-1.0.txt
fret_analysis-3.1.0.dist-info/RECORD
