Metadata-Version: 2.4
Name: fret-analysis
Version: 3.1.0
Summary: Tools for analyzing single-molecule FRET data
Project-URL: Repository, https://github.com/schuetzgroup/fret-analysis
Author-email: Lukas Schrangl <lukas.schrangl@boku.ac.at>
License-File: LICENSES/BSD-3-Clause.txt
License-File: LICENSES/CC-BY-4.0.txt
License-File: LICENSES/CC0-1.0.txt
Classifier: Development Status :: 5 - Production/Stable
Classifier: Intended Audience :: Science/Research
Classifier: License :: OSI Approved :: BSD License
Classifier: Operating System :: OS Independent
Classifier: Programming Language :: Python :: 3
Classifier: Programming Language :: Python :: 3 :: Only
Classifier: Topic :: Scientific/Engineering
Classifier: Topic :: Scientific/Engineering :: Bio-Informatics
Classifier: Topic :: Scientific/Engineering :: Image Processing
Classifier: Topic :: Scientific/Engineering :: Information Analysis
Classifier: Topic :: Scientific/Engineering :: Physics
Requires-Python: >=3.10
Requires-Dist: ipympl
Requires-Dist: ipywidgets
Requires-Dist: matplotlib
Requires-Dist: numba
Requires-Dist: numpy
Requires-Dist: pandas
Requires-Dist: pims
Requires-Dist: scikit-learn
Requires-Dist: scipy
Requires-Dist: sdt-python
Requires-Dist: trackpy
